<?xml version='1.0' encoding="UTF-8"?>
<vocabulary>
  <name>POTTER</name>
  <languages>
    <language1>CZ</language1>
    <language2>NJ</language2>
  </languages>
  <words>
    <word><L1>nato</L1><L2>darauf</L2></word>
    <word><L1>hrdý</L1><L2>stolz</L2></word>
    <word><L1>vše</L1><L2>ganz</L2></word>
    <word><L1>jeho</L1><L2>sein</L2></word>
    <word><L1>velmi</L1><L2>sehr</L2></word>
    <word><L1>kéž</L1><L2>wäre</L2></word>
    <word><L1>přijít</L1><L2>gekommen</L2></word>
    <word><L1>mohl</L1><L2>könnten</L2></word>
    <word><L1>sám</L1><L2>sich</L2></word>
    <word><L1>protože</L1><L2>denn</L2></word>
    <word><L1>takový</L1><L2>ein solcher</L2></word>
    <word><L1>chtít</L1><L2>wollen</L2></word>
    <word><L1>čaroděj</L1><L2>r Zauberer</L2></word>
  </words>
</vocabulary>
