<?xml version='1.0' encoding="UTF-8"?>
<vocabulary>
  <name>Klettern</name>
  <languages>
    <language1>EN</language1>
    <language2>NJ</language2>
  </languages>
  <words>
    <word><L1>Abseiling</L1><L2>Abseilen</L2></word>
    <word><L1>Rope</L1><L2>Seil</L2></word>
    <word><L1>Rock</L1><L2>Stein</L2></word>
    <word><L1>Climbing</L1><L2>Klettern</L2></word>
    <word><L1>Cesta</L1><L2>Weg</L2></word>
    <word><L1>Quickdraw</L1><L2>Expreßschlinge</L2></word>
    <word><L1>Sling</L1><L2>Schlinge</L2></word>
    <word><L1>Belay</L1><L2>Sichern</L2></word>
    <word><L1>hold</L1><L2>Griff</L2></word>
    <word><L1>Tunnel (hodiny)</L1><L2>Sanduhr</L2></word>
    <word><L1>Crag, Rock</L1><L2>Felsen</L2></word>
    <word><L1>Corner</L1><L2>Winkel, Nische, Ecke</L2></word>
    <word><L1>Arete</L1><L2>Kante</L2></word>
    <word><L1>Couloir</L1><L2>Rinne</L2></word>
    <word><L1>Crack</L1><L2>Riß</L2></word>
    <word><L1>Chimney</L1><L2>Kamin</L2></word>
    <word><L1>Ledge</L1><L2>Leiste</L2></word>
    <word><L1>Overhang</L1><L2>Überhang</L2></word>
    <word><L1>Pillar</L1><L2>Pfeiler</L2></word>
    <word><L1>Slab (plotna)</L1><L2>Platte</L2></word>
    <word><L1>Rib (žebro)</L1><L2>Rippe</L2></word>
    <word><L1>Piton (skoba)</L1><L2>Haken</L2></word>
    <word><L1>Anchor</L1><L2>Verankerung</L2></word>
    <word><L1>Bolt</L1><L2>Haken</L2></word>
    <word><L1>Fall</L1><L2>Sturz</L2></word>
    <word><L1>Belayer</L1><L2>Sicherungsmann</L2></word>
    <word><L1>Climbing gym</L1><L2>Kletterhalle</L2></word>
    <word><L1>Climbing shoes</L1><L2>Kletterschuhe</L2></word>
    <word><L1>Handjam</L1><L2>Handklemmer</L2></word>
    <word><L1>Harness</L1><L2>Klettergurt</L2></word>
    <word><L1>Nut</L1><L2>Klemmkeil</L2></word>
  </words>
</vocabulary>
